[
  {
    "trend_arrow": "FLAT", 
    "display_time": "2016-10-05T00:14:36-07:00", 
    "noise": 1, 
    "system_time": "2016-10-05T07:03:01-07:00", 
    "direction": "Flat", 
    "sgv": 169, 
    "dateString": "2016-10-05T00:14:36-07:00", 
    "date": 1475651676000, 
    "unfiltered": 182528, 
    "filtered": 189184, 
    "device": "openaps://indy-e1/cgm", 
    "rssi": 436, 
    "type": "sgv", 
    "glucose": 169
  }, 
  {
    "trend_arrow": "FLAT", 
    "display_time": "2016-10-05T00:09:36-07:00", 
    "noise": 1, 
    "system_time": "2016-10-05T06:58:01-07:00", 
    "direction": "Flat", 
    "sgv": 175, 
    "dateString": "2016-10-05T00:09:36-07:00", 
    "date": 1475651376000, 
    "unfiltered": 187392, 
    "filtered": 190368, 
    "device": "openaps://indy-e1/cgm", 
    "rssi": 437, 
    "type": "sgv", 
    "glucose": 175
  }
]