[
  {
    "trend_arrow": "FLAT", 
    "display_time": "2016-10-04T12:49:38-07:00", 
    "noise": 1, 
    "system_time": "2016-10-04T19:38:02-07:00", 
    "direction": "Flat", 
    "sgv": 101, 
    "dateString": "2016-10-04T12:49:38-07:00", 
    "date": 1475610578000, 
    "unfiltered": 120064, 
    "filtered": 114672, 
    "device": "openaps://indy-e1/cgm", 
    "rssi": 206, 
    "type": "sgv", 
    "glucose": 101
  }, 
  {
    "trend_arrow": "FLAT", 
    "display_time": "2016-10-04T12:44:38-07:00", 
    "noise": 1, 
    "system_time": "2016-10-04T19:33:02-07:00", 
    "direction": "Flat", 
    "sgv": 97, 
    "dateString": "2016-10-04T12:44:38-07:00", 
    "date": 1475610278000, 
    "unfiltered": 116688, 
    "filtered": 113504, 
    "device": "openaps://indy-e1/cgm", 
    "rssi": 205, 
    "type": "sgv", 
    "glucose": 97
  }
]