[
  {
    "trend_arrow": "SINGLE_DOWN", 
    "display_time": "2016-09-29T23:40:04-07:00", 
    "noise": 1, 
    "system_time": "2016-09-30T05:34:10-07:00", 
    "direction": "SingleDown", 
    "sgv": 118, 
    "dateString": "2016-09-29T23:40:04-07:00", 
    "date": 1475217604000, 
    "unfiltered": 113600, 
    "filtered": 125504, 
    "device": "openaps://indy-e1/cgm", 
    "rssi": 187, 
    "type": "sgv", 
    "glucose": 118
  }, 
  {
    "trend_arrow": "SINGLE_DOWN", 
    "display_time": "2016-09-29T23:35:04-07:00", 
    "noise": 1, 
    "system_time": "2016-09-30T05:29:10-07:00", 
    "direction": "SingleDown", 
    "sgv": 117, 
    "dateString": "2016-09-29T23:35:04-07:00", 
    "date": 1475217304000, 
    "unfiltered": 112896, 
    "filtered": 132768, 
    "device": "openaps://indy-e1/cgm", 
    "rssi": 191, 
    "type": "sgv", 
    "glucose": 117
  }
]