[
  {
    "trend_arrow": "FLAT", 
    "display_time": "2016-10-08T01:09:35-07:00", 
    "noise": 1, 
    "system_time": "2016-10-08T07:03:25-07:00", 
    "direction": "Flat", 
    "sgv": 96, 
    "dateString": "2016-10-08T01:09:35-07:00", 
    "date": 1475914175000, 
    "unfiltered": 113456, 
    "filtered": 110640, 
    "device": "openaps://indy-e1/cgm", 
    "rssi": 182, 
    "type": "sgv", 
    "glucose": 96
  }, 
  {
    "trend_arrow": "FLAT", 
    "display_time": "2016-10-08T01:04:35-07:00", 
    "noise": 1, 
    "system_time": "2016-10-08T06:58:25-07:00", 
    "direction": "Flat", 
    "sgv": 94, 
    "dateString": "2016-10-08T01:04:35-07:00", 
    "date": 1475913875000, 
    "unfiltered": 111616, 
    "filtered": 109472, 
    "device": "openaps://indy-e1/cgm", 
    "rssi": 182, 
    "type": "sgv", 
    "glucose": 94
  }
]