[
  {
    "trend_arrow": "SINGLE_UP", 
    "display_time": "2016-09-30T14:29:51-07:00", 
    "noise": 1, 
    "system_time": "2016-09-30T21:18:16-07:00", 
    "direction": "SingleUp", 
    "sgv": 216, 
    "dateString": "2016-09-30T14:29:51-07:00", 
    "date": 1475270991000, 
    "unfiltered": 187648, 
    "filtered": 176032, 
    "device": "openaps://indy-e1/cgm", 
    "rssi": 204, 
    "type": "sgv", 
    "glucose": 216
  }, 
  {
    "trend_arrow": "SINGLE_UP", 
    "display_time": "2016-09-30T14:24:51-07:00", 
    "noise": 1, 
    "system_time": "2016-09-30T21:13:16-07:00", 
    "direction": "SingleUp", 
    "sgv": 207, 
    "dateString": "2016-09-30T14:24:51-07:00", 
    "date": 1475270691000, 
    "unfiltered": 180320, 
    "filtered": 164896, 
    "device": "openaps://indy-e1/cgm", 
    "rssi": 210, 
    "type": "sgv", 
    "glucose": 207
  }
]