[
  {
    "trend_arrow": "FLAT", 
    "display_time": "2016-10-04T13:54:37-07:00", 
    "noise": 1, 
    "system_time": "2016-10-04T20:43:02-07:00", 
    "direction": "Flat", 
    "sgv": 120, 
    "dateString": "2016-10-04T13:54:37-07:00", 
    "date": 1475614477000, 
    "unfiltered": 137696, 
    "filtered": 135008, 
    "device": "openaps://indy-e1/cgm", 
    "rssi": 208, 
    "type": "sgv", 
    "glucose": 120
  }, 
  {
    "trend_arrow": "FLAT", 
    "display_time": "2016-10-04T13:49:38-07:00", 
    "noise": 1, 
    "system_time": "2016-10-04T20:38:02-07:00", 
    "direction": "Flat", 
    "sgv": 117, 
    "dateString": "2016-10-04T13:49:38-07:00", 
    "date": 1475614178000, 
    "unfiltered": 134656, 
    "filtered": 131968, 
    "device": "openaps://indy-e1/cgm", 
    "rssi": 208, 
    "type": "sgv", 
    "glucose": 117
  }
]