[
  {
    "trend_arrow": "FLAT", 
    "display_time": "2016-10-06T07:34:31-07:00", 
    "noise": 1, 
    "system_time": "2016-10-06T14:22:56-07:00", 
    "direction": "Flat", 
    "sgv": 120, 
    "dateString": "2016-10-06T07:34:31-07:00", 
    "date": 1475764471000, 
    "unfiltered": 138784, 
    "filtered": 141568, 
    "device": "openaps://indy-e1/cgm", 
    "rssi": 190, 
    "type": "sgv", 
    "glucose": 120
  }, 
  {
    "trend_arrow": "FLAT", 
    "display_time": "2016-10-06T07:29:31-07:00", 
    "noise": 1, 
    "system_time": "2016-10-06T14:17:56-07:00", 
    "direction": "Flat", 
    "sgv": 121, 
    "dateString": "2016-10-06T07:29:31-07:00", 
    "date": 1475764171000, 
    "unfiltered": 139136, 
    "filtered": 144064, 
    "device": "openaps://indy-e1/cgm", 
    "rssi": 190, 
    "type": "sgv", 
    "glucose": 121
  }
]