[
  {
    "trend_arrow": "45_DOWN", 
    "display_time": "2016-09-30T05:15:03-07:00", 
    "noise": 1, 
    "direction": "FortyFiveDown", 
    "system_time": "2016-09-30T11:09:09-07:00", 
    "sgv": 119, 
    "dateString": "2016-09-30T05:15:03-07:00", 
    "device": "openaps://indy-e1/cgm", 
    "unfiltered": 108160, 
    "rssi": 192, 
    "date": 1475237703000.0, 
    "filtered": 113872, 
    "type": "sgv", 
    "glucose": 119
  }, 
  {
    "trend_arrow": "45_DOWN", 
    "display_time": "2016-09-30T05:10:03-07:00", 
    "noise": 1, 
    "direction": "FortyFiveDown", 
    "system_time": "2016-09-30T11:04:09-07:00", 
    "sgv": 125, 
    "dateString": "2016-09-30T05:10:03-07:00", 
    "device": "openaps://indy-e1/cgm", 
    "unfiltered": 111424, 
    "rssi": 187, 
    "date": 1475237403000.0, 
    "filtered": 116624, 
    "type": "sgv", 
    "glucose": 125
  }, 
  {
    "trend_arrow": "FLAT", 
    "display_time": "2016-09-30T05:05:03-07:00", 
    "noise": 1, 
    "direction": "Flat", 
    "system_time": "2016-09-30T10:59:09-07:00", 
    "sgv": 133, 
    "dateString": "2016-09-30T05:05:03-07:00", 
    "device": "openaps://indy-e1/cgm", 
    "unfiltered": 115664, 
    "rssi": 187, 
    "date": 1475237103000.0, 
    "filtered": 119264, 
    "type": "sgv", 
    "glucose": 133
  }, 
  {
    "trend_arrow": "FLAT", 
    "display_time": "2016-09-30T05:00:03-07:00", 
    "noise": 1, 
    "direction": "Flat", 
    "system_time": "2016-09-30T10:54:09-07:00", 
    "sgv": 140, 
    "dateString": "2016-09-30T05:00:03-07:00", 
    "device": "openaps://indy-e1/cgm", 
    "unfiltered": 119536, 
    "rssi": 187, 
    "date": 1475236803000.0, 
    "filtered": 122368, 
    "type": "sgv", 
    "glucose": 140
  }, 
  {
    "trend_arrow": "FLAT", 
    "display_time": "2016-09-30T04:55:03-07:00", 
    "noise": 1, 
    "direction": "Flat", 
    "system_time": "2016-09-30T10:49:09-07:00", 
    "sgv": 141, 
    "dateString": "2016-09-30T04:55:03-07:00", 
    "device": "openaps://indy-e1/cgm", 
    "unfiltered": 120000, 
    "rssi": 183, 
    "date": 1475236503000.0, 
    "filtered": 125360, 
    "type": "sgv", 
    "glucose": 141
  }, 
  {
    "trend_arrow": "FLAT", 
    "display_time": "2016-09-30T04:50:04-07:00", 
    "noise": 1, 
    "direction": "Flat", 
    "system_time": "2016-09-30T10:44:09-07:00", 
    "sgv": 144, 
    "dateString": "2016-09-30T04:50:04-07:00", 
    "device": "openaps://indy-e1/cgm", 
    "unfiltered": 121648, 
    "rssi": 428, 
    "date": 1475236204000.0, 
    "filtered": 126816, 
    "type": "sgv", 
    "glucose": 144
  }
]