[
  {
    "trend_arrow": "FLAT", 
    "display_time": "2016-10-07T06:59:38-07:00", 
    "noise": 1, 
    "system_time": "2016-10-07T12:53:27-07:00", 
    "direction": "Flat", 
    "sgv": 125, 
    "dateString": "2016-10-07T06:59:38-07:00", 
    "device": "openaps://indy-e1/cgm", 
    "unfiltered": 141920, 
    "rssi": 201, 
    "date": 1475848778000, 
    "filtered": 139840, 
    "type": "sgv", 
    "glucose": 125
  }, 
  {
    "trend_arrow": "FLAT", 
    "display_time": "2016-10-07T06:54:38-07:00", 
    "noise": 1, 
    "system_time": "2016-10-07T12:48:27-07:00", 
    "direction": "Flat", 
    "sgv": 124, 
    "dateString": "2016-10-07T06:54:38-07:00", 
    "device": "openaps://indy-e1/cgm", 
    "unfiltered": 140768, 
    "rssi": 185, 
    "date": 1475848478000, 
    "filtered": 135744, 
    "type": "sgv", 
    "glucose": 124
  }
]