[
  {
    "trend_arrow": "FLAT", 
    "display_time": "2016-10-08T01:24:36-07:00", 
    "noise": 1, 
    "direction": "Flat", 
    "system_time": "2016-10-08T07:18:25-07:00", 
    "sgv": 104, 
    "dateString": "2016-10-08T01:24:36-07:00", 
    "device": "openaps://indy-e1/cgm", 
    "unfiltered": 121024, 
    "rssi": 448, 
    "date": 1475915076000.0, 
    "filtered": 116768, 
    "type": "sgv", 
    "glucose": 104
  }, 
  {
    "trend_arrow": "FLAT", 
    "display_time": "2016-10-08T01:19:35-07:00", 
    "noise": 1, 
    "direction": "Flat", 
    "system_time": "2016-10-08T07:13:25-07:00", 
    "sgv": 101, 
    "dateString": "2016-10-08T01:19:35-07:00", 
    "device": "openaps://indy-e1/cgm", 
    "unfiltered": 118304, 
    "rssi": 187, 
    "date": 1475914775000.0, 
    "filtered": 114320, 
    "type": "sgv", 
    "glucose": 101
  }, 
  {
    "trend_arrow": "FLAT", 
    "display_time": "2016-10-08T01:14:35-07:00", 
    "noise": 1, 
    "direction": "Flat", 
    "system_time": "2016-10-08T07:08:25-07:00", 
    "sgv": 98, 
    "dateString": "2016-10-08T01:14:35-07:00", 
    "device": "openaps://indy-e1/cgm", 
    "unfiltered": 115520, 
    "rssi": 189, 
    "date": 1475914475000.0, 
    "filtered": 112240, 
    "type": "sgv", 
    "glucose": 98
  }, 
  {
    "trend_arrow": "FLAT", 
    "display_time": "2016-10-08T01:09:35-07:00", 
    "noise": 1, 
    "direction": "Flat", 
    "system_time": "2016-10-08T07:03:25-07:00", 
    "sgv": 96, 
    "dateString": "2016-10-08T01:09:35-07:00", 
    "device": "openaps://indy-e1/cgm", 
    "unfiltered": 113456, 
    "rssi": 182, 
    "date": 1475914175000.0, 
    "filtered": 110640, 
    "type": "sgv", 
    "glucose": 96
  }, 
  {
    "trend_arrow": "FLAT", 
    "display_time": "2016-10-08T01:04:35-07:00", 
    "noise": 1, 
    "direction": "Flat", 
    "system_time": "2016-10-08T06:58:25-07:00", 
    "sgv": 94, 
    "dateString": "2016-10-08T01:04:35-07:00", 
    "device": "openaps://indy-e1/cgm", 
    "unfiltered": 111616, 
    "rssi": 182, 
    "date": 1475913875000.0, 
    "filtered": 109472, 
    "type": "sgv", 
    "glucose": 94
  }, 
  {
    "trend_arrow": "FLAT", 
    "display_time": "2016-10-08T00:59:35-07:00", 
    "noise": 1, 
    "direction": "Flat", 
    "system_time": "2016-10-08T06:53:25-07:00", 
    "sgv": 92, 
    "dateString": "2016-10-08T00:59:35-07:00", 
    "device": "openaps://indy-e1/cgm", 
    "unfiltered": 109792, 
    "rssi": 181, 
    "date": 1475913575000.0, 
    "filtered": 108416, 
    "type": "sgv", 
    "glucose": 92
  }
]