[
  {
    "trend_arrow": "FLAT", 
    "display_time": "2016-10-04T20:24:36-07:00", 
    "noise": 1, 
    "system_time": "2016-10-05T03:13:01-07:00", 
    "direction": "Flat", 
    "sgv": 135, 
    "dateString": "2016-10-04T20:24:36-07:00", 
    "device": "openaps://indy-e1/cgm", 
    "unfiltered": 151712, 
    "rssi": 217, 
    "date": 1475637876000, 
    "filtered": 149120, 
    "type": "sgv", 
    "glucose": 135
  }, 
  {
    "trend_arrow": "45_UP", 
    "display_time": "2016-10-04T20:19:36-07:00", 
    "noise": 1, 
    "system_time": "2016-10-05T03:08:01-07:00", 
    "direction": "FortyFiveUp", 
    "sgv": 134, 
    "dateString": "2016-10-04T20:19:36-07:00", 
    "device": "openaps://indy-e1/cgm", 
    "unfiltered": 150720, 
    "rssi": 211, 
    "date": 1475637576000, 
    "filtered": 145056, 
    "type": "sgv", 
    "glucose": 134
  }
]