[
  {
    "trend_arrow": "45_DOWN", 
    "display_time": "2016-10-09T00:24:32-07:00", 
    "noise": 1, 
    "direction": "FortyFiveDown", 
    "system_time": "2016-10-09T06:18:22-07:00", 
    "sgv": 145, 
    "dateString": "2016-10-09T00:24:32-07:00", 
    "device": "openaps://indy-e1/cgm", 
    "unfiltered": 161664, 
    "rssi": 450, 
    "date": 1475997872000.0, 
    "filtered": 170208, 
    "type": "sgv", 
    "glucose": 145
  }, 
  {
    "trend_arrow": "45_DOWN", 
    "display_time": "2016-10-09T00:19:32-07:00", 
    "noise": 1, 
    "direction": "FortyFiveDown", 
    "system_time": "2016-10-09T06:13:22-07:00", 
    "sgv": 151, 
    "dateString": "2016-10-09T00:19:32-07:00", 
    "device": "openaps://indy-e1/cgm", 
    "unfiltered": 167680, 
    "rssi": 452, 
    "date": 1475997572000.0, 
    "filtered": 176416, 
    "type": "sgv", 
    "glucose": 151
  }, 
  {
    "trend_arrow": "45_DOWN", 
    "display_time": "2016-10-09T00:14:32-07:00", 
    "noise": 1, 
    "direction": "FortyFiveDown", 
    "system_time": "2016-10-09T06:08:21-07:00", 
    "sgv": 156, 
    "dateString": "2016-10-09T00:14:32-07:00", 
    "device": "openaps://indy-e1/cgm", 
    "unfiltered": 172992, 
    "rssi": 193, 
    "date": 1475997272000.0, 
    "filtered": 182688, 
    "type": "sgv", 
    "glucose": 156
  }, 
  {
    "trend_arrow": "45_DOWN", 
    "display_time": "2016-10-09T00:09:32-07:00", 
    "noise": 1, 
    "direction": "FortyFiveDown", 
    "system_time": "2016-10-09T06:03:21-07:00", 
    "sgv": 162, 
    "dateString": "2016-10-09T00:09:32-07:00", 
    "device": "openaps://indy-e1/cgm", 
    "unfiltered": 178496, 
    "rssi": 191, 
    "date": 1475996972000.0, 
    "filtered": 188256, 
    "type": "sgv", 
    "glucose": 162
  }, 
  {
    "trend_arrow": "FLAT", 
    "display_time": "2016-10-09T00:04:32-07:00", 
    "noise": 1, 
    "direction": "Flat", 
    "system_time": "2016-10-09T05:58:21-07:00", 
    "sgv": 169, 
    "dateString": "2016-10-09T00:04:32-07:00", 
    "device": "openaps://indy-e1/cgm", 
    "unfiltered": 184832, 
    "rssi": 193, 
    "date": 1475996672000.0, 
    "filtered": 192704, 
    "type": "sgv", 
    "glucose": 169
  }, 
  {
    "trend_arrow": "FLAT", 
    "display_time": "2016-10-08T23:59:32-07:00", 
    "noise": 1, 
    "direction": "Flat", 
    "system_time": "2016-10-09T05:53:21-07:00", 
    "sgv": 176, 
    "dateString": "2016-10-08T23:59:32-07:00", 
    "device": "openaps://indy-e1/cgm", 
    "unfiltered": 191680, 
    "rssi": 193, 
    "date": 1475996372000.0, 
    "filtered": 196256, 
    "type": "sgv", 
    "glucose": 176
  }
]