[
  {
    "trend_arrow": "FLAT", 
    "system_time": "2016-10-03T17:38:06", 
    "noise": 1, 
    "direction": "Flat", 
    "sgv": 161, 
    "display_time": "2016-10-03T10:49:41", 
    "date": 1475516981000.0, 
    "dateString": "2016-10-03T10:49:41", 
    "unfiltered": 180448, 
    "filtered": 187104, 
    "device": "openaps://indy-e1/cgm", 
    "rssi": 185, 
    "type": "sgv", 
    "glucose": 161
  }, 
  {
    "trend_arrow": "FLAT", 
    "system_time": "2016-10-03T17:33:06", 
    "noise": 1, 
    "direction": "Flat", 
    "sgv": 170, 
    "display_time": "2016-10-03T10:44:41", 
    "date": 1475516681000.0, 
    "dateString": "2016-10-03T10:44:41", 
    "unfiltered": 190656, 
    "filtered": 185056, 
    "device": "openaps://indy-e1/cgm", 
    "rssi": 209, 
    "type": "sgv", 
    "glucose": 170
  }, 
  {
    "trend_arrow": "FLAT", 
    "system_time": "2016-10-03T17:28:06", 
    "noise": 1, 
    "direction": "Flat", 
    "sgv": 172, 
    "display_time": "2016-10-03T10:39:41", 
    "date": 1475516381000.0, 
    "dateString": "2016-10-03T10:39:41", 
    "unfiltered": 192032, 
    "filtered": 183648, 
    "device": "openaps://indy-e1/cgm", 
    "rssi": 204, 
    "type": "sgv", 
    "glucose": 172
  }, 
  {
    "trend_arrow": "FLAT", 
    "system_time": "2016-10-03T17:23:06", 
    "noise": 1, 
    "direction": "Flat", 
    "sgv": 162, 
    "display_time": "2016-10-03T10:34:41", 
    "date": 1475516081000.0, 
    "dateString": "2016-10-03T10:34:41", 
    "unfiltered": 181248, 
    "filtered": 183904, 
    "device": "openaps://indy-e1/cgm", 
    "rssi": 196, 
    "type": "sgv", 
    "glucose": 162
  }, 
  {
    "trend_arrow": "FLAT", 
    "system_time": "2016-10-03T17:18:06", 
    "noise": 1, 
    "direction": "Flat", 
    "sgv": 161, 
    "display_time": "2016-10-03T10:29:41", 
    "date": 1475515781000.0, 
    "dateString": "2016-10-03T10:29:41", 
    "unfiltered": 180960, 
    "filtered": 183488, 
    "device": "openaps://indy-e1/cgm", 
    "rssi": 210, 
    "type": "sgv", 
    "glucose": 161
  }, 
  {
    "trend_arrow": "FLAT", 
    "system_time": "2016-10-03T17:13:06", 
    "noise": 1, 
    "direction": "Flat", 
    "sgv": 164, 
    "display_time": "2016-10-03T10:24:41", 
    "date": 1475515481000.0, 
    "dateString": "2016-10-03T10:24:41", 
    "unfiltered": 183712, 
    "filtered": 180448, 
    "device": "openaps://indy-e1/cgm", 
    "rssi": 187, 
    "type": "sgv", 
    "glucose": 164
  }
]