[
  {
    "trend_arrow": "FLAT", 
    "display_time": "2016-09-30T04:05:03-07:00", 
    "noise": 1, 
    "direction": "Flat", 
    "system_time": "2016-09-30T09:59:09-07:00", 
    "sgv": 116, 
    "dateString": "2016-09-30T04:05:03-07:00", 
    "device": "openaps://indy-e1/cgm", 
    "unfiltered": 106704, 
    "rssi": 194, 
    "date": 1475233503000.0, 
    "filtered": 104928, 
    "type": "sgv", 
    "glucose": 116
  }, 
  {
    "trend_arrow": "FLAT", 
    "display_time": "2016-09-30T04:00:03-07:00", 
    "noise": 1, 
    "direction": "Flat", 
    "system_time": "2016-09-30T09:54:09-07:00", 
    "sgv": 113, 
    "dateString": "2016-09-30T04:00:03-07:00", 
    "device": "openaps://indy-e1/cgm", 
    "unfiltered": 104944, 
    "rssi": 194, 
    "date": 1475233203000.0, 
    "filtered": 103616, 
    "type": "sgv", 
    "glucose": 113
  }, 
  {
    "trend_arrow": "FLAT", 
    "display_time": "2016-09-30T03:55:04-07:00", 
    "noise": 1, 
    "direction": "Flat", 
    "system_time": "2016-09-30T09:49:09-07:00", 
    "sgv": 110, 
    "dateString": "2016-09-30T03:55:04-07:00", 
    "device": "openaps://indy-e1/cgm", 
    "unfiltered": 103584, 
    "rssi": 195, 
    "date": 1475232904000.0, 
    "filtered": 101856, 
    "type": "sgv", 
    "glucose": 110
  }, 
  {
    "trend_arrow": "FLAT", 
    "display_time": "2016-09-30T03:50:04-07:00", 
    "noise": 1, 
    "direction": "Flat", 
    "system_time": "2016-09-30T09:44:09-07:00", 
    "sgv": 111, 
    "dateString": "2016-09-30T03:50:04-07:00", 
    "device": "openaps://indy-e1/cgm", 
    "unfiltered": 104288, 
    "rssi": 195, 
    "date": 1475232604000.0, 
    "filtered": 99984, 
    "type": "sgv", 
    "glucose": 111
  }, 
  {
    "trend_arrow": "FLAT", 
    "display_time": "2016-09-30T03:45:04-07:00", 
    "noise": 1, 
    "direction": "Flat", 
    "system_time": "2016-09-30T09:39:09-07:00", 
    "sgv": 105, 
    "dateString": "2016-09-30T03:45:04-07:00", 
    "device": "openaps://indy-e1/cgm", 
    "unfiltered": 101056, 
    "rssi": 193, 
    "date": 1475232304000.0, 
    "filtered": 98256, 
    "type": "sgv", 
    "glucose": 105
  }, 
  {
    "trend_arrow": "FLAT", 
    "display_time": "2016-09-30T03:40:04-07:00", 
    "noise": 1, 
    "direction": "Flat", 
    "system_time": "2016-09-30T09:34:09-07:00", 
    "sgv": 100, 
    "dateString": "2016-09-30T03:40:04-07:00", 
    "device": "openaps://indy-e1/cgm", 
    "unfiltered": 97936, 
    "rssi": 196, 
    "date": 1475232004000.0, 
    "filtered": 97072, 
    "type": "sgv", 
    "glucose": 100
  }
]