[
  {
    "trend_arrow": "FLAT", 
    "display_time": "2016-10-05T10:34:34-07:00", 
    "noise": 1, 
    "system_time": "2016-10-05T17:22:59-07:00", 
    "direction": "Flat", 
    "sgv": 133, 
    "dateString": "2016-10-05T10:34:34-07:00", 
    "device": "openaps://indy-e1/cgm", 
    "unfiltered": 150080, 
    "rssi": 191, 
    "date": 1475688874000, 
    "filtered": 150656, 
    "type": "sgv", 
    "glucose": 133
  }, 
  {
    "trend_arrow": "45_UP", 
    "display_time": "2016-10-05T10:29:34-07:00", 
    "noise": 1, 
    "system_time": "2016-10-05T17:17:59-07:00", 
    "direction": "FortyFiveUp", 
    "sgv": 134, 
    "dateString": "2016-10-05T10:29:34-07:00", 
    "device": "openaps://indy-e1/cgm", 
    "unfiltered": 151680, 
    "rssi": 180, 
    "date": 1475688574000, 
    "filtered": 144160, 
    "type": "sgv", 
    "glucose": 134
  }
]