[
  {
    "trend_arrow": "FLAT", 
    "display_time": "2016-10-06T03:19:32-07:00", 
    "noise": 1, 
    "system_time": "2016-10-06T10:07:56-07:00", 
    "direction": "Flat", 
    "sgv": 109, 
    "dateString": "2016-10-06T03:19:32-07:00", 
    "device": "openaps://indy-e1/cgm", 
    "unfiltered": 129552, 
    "rssi": 189, 
    "date": 1475749172000, 
    "filtered": 135616, 
    "type": "sgv", 
    "glucose": 109
  }, 
  {
    "trend_arrow": "FLAT", 
    "display_time": "2016-10-06T03:14:32-07:00", 
    "noise": 1, 
    "system_time": "2016-10-06T10:02:56-07:00", 
    "direction": "Flat", 
    "sgv": 112, 
    "dateString": "2016-10-06T03:14:32-07:00", 
    "device": "openaps://indy-e1/cgm", 
    "unfiltered": 131776, 
    "rssi": 186, 
    "date": 1475748872000, 
    "filtered": 138240, 
    "type": "sgv", 
    "glucose": 112
  }
]