[
  {
    "trend_arrow": "FLAT", 
    "system_time": "2016-09-30T01:04:11", 
    "noise": 1, 
    "direction": "Flat", 
    "sgv": 125, 
    "display_time": "2016-09-29T19:10:05", 
    "date": 1475201405000.0, 
    "dateString": "2016-09-29T19:10:05", 
    "unfiltered": 126368, 
    "filtered": 126784, 
    "device": "openaps://indy-e1/cgm", 
    "rssi": 196, 
    "type": "sgv", 
    "glucose": 125
  }, 
  {
    "trend_arrow": "FLAT", 
    "system_time": "2016-09-30T00:59:11", 
    "noise": 1, 
    "direction": "Flat", 
    "sgv": 129, 
    "display_time": "2016-09-29T19:05:05", 
    "date": 1475201105000.0, 
    "dateString": "2016-09-29T19:05:05", 
    "unfiltered": 129728, 
    "filtered": 122144, 
    "device": "openaps://indy-e1/cgm", 
    "rssi": 185, 
    "type": "sgv", 
    "glucose": 129
  }, 
  {
    "trend_arrow": "FLAT", 
    "system_time": "2016-09-30T00:54:11", 
    "noise": 1, 
    "direction": "Flat", 
    "sgv": 128, 
    "display_time": "2016-09-29T19:00:05", 
    "date": 1475200805000.0, 
    "dateString": "2016-09-29T19:00:05", 
    "unfiltered": 128384, 
    "filtered": 119216, 
    "device": "openaps://indy-e1/cgm", 
    "rssi": 189, 
    "type": "sgv", 
    "glucose": 128
  }, 
  {
    "trend_arrow": "FLAT", 
    "system_time": "2016-09-30T00:49:11", 
    "noise": 1, 
    "direction": "Flat", 
    "sgv": 120, 
    "display_time": "2016-09-29T18:55:05", 
    "date": 1475200505000.0, 
    "dateString": "2016-09-29T18:55:05", 
    "unfiltered": 122304, 
    "filtered": 121520, 
    "device": "openaps://indy-e1/cgm", 
    "rssi": 197, 
    "type": "sgv", 
    "glucose": 120
  }, 
  {
    "trend_arrow": "45_DOWN", 
    "system_time": "2016-09-30T00:44:11", 
    "noise": 1, 
    "direction": "FortyFiveDown", 
    "sgv": 116, 
    "display_time": "2016-09-29T18:50:05", 
    "date": 1475200205000.0, 
    "dateString": "2016-09-29T18:50:05", 
    "unfiltered": 119440, 
    "filtered": 128592, 
    "device": "openaps://indy-e1/cgm", 
    "rssi": 196, 
    "type": "sgv", 
    "glucose": 116
  }, 
  {
    "trend_arrow": "NOT_COMPUTABLE", 
    "system_time": "2016-09-30T00:39:13", 
    "noise": 3, 
    "direction": "NOT COMPUTABLE", 
    "sgv": 136, 
    "display_time": "2016-09-29T18:45:07", 
    "date": 1475199907000.0, 
    "dateString": "2016-09-29T18:45:07", 
    "unfiltered": 121888, 
    "filtered": 134944, 
    "device": "openaps://indy-e1/cgm", 
    "rssi": 182, 
    "type": "sgv", 
    "glucose": 136
  }, 
  {
    "trend_arrow": "NOT_COMPUTABLE", 
    "system_time": "2016-09-30T00:39:12", 
    "noise": 3, 
    "direction": "NOT COMPUTABLE", 
    "sgv": 135, 
    "display_time": "2016-09-29T18:45:07", 
    "date": 1475199907000.0, 
    "dateString": "2016-09-29T18:45:07", 
    "device": "openaps://indy-e1/cgm", 
    "type": "sgv", 
    "glucose": 135
  }
]